falcon_router/__init__.py
falcon_router/router.py
falcon_router-0.0.4.dist-info/LICENSE
falcon_router-0.0.4.dist-info/METADATA
falcon_router-0.0.4.dist-info/WHEEL
falcon_router-0.0.4.dist-info/top_level.txt
falcon_router-0.0.4.dist-info/RECORD
