Metadata-Version: 2.1
Name: falcon-router
Version: 0.0.4
Summary: Simple router for Falcon framework
Home-page: https://gitlab.com/vojko.pribudic/falcon-router
Author: Vojko Pribudić
Author-email: dmanthing@gmail.com
Project-URL: Bug Tracker, https://gitlab.com/vojko.pribudic/falcon-router/-/issues
Classifier: Programming Language :: Python :: 3
Classifier: License :: OSI Approved :: MIT License
Classifier: Operating System :: OS Independent
Requires-Python: >=3.6
License-File: LICENSE
Requires-Dist: falcon
